reg_resampler.py
reg_resampler-2.1.1.dist-info/LICENSE
reg_resampler-2.1.1.dist-info/METADATA
reg_resampler-2.1.1.dist-info/WHEEL
reg_resampler-2.1.1.dist-info/top_level.txt
reg_resampler-2.1.1.dist-info/RECORD
