Metadata-Version: 2.1
Name: reg-resampler
Version: 2.1.1
Summary: An interface to apply your favourite re-sampler on regression tasks.
Home-page: https://github.com/atif-hassan/Regression_ReSampling/
Author: Atif Hassan, Venkata Sai Krithik
Author-email: atif.hit.hassan@gmail.com, pvsaikrithik@gmail.com
License: UNKNOWN
Platform: UNKNOWN
Classifier: Programming Language :: Python :: 3
Classifier: Programming Language :: Python :: 3.6
Classifier: Programming Language :: Python :: 3.7
Classifier: License :: OSI Approved :: BSD License
Classifier: Operating System :: OS Independent
Requires-Dist: pandas
Requires-Dist: scikit-learn
Requires-Dist: numpy
